setup.cfg
setup.py
zipper.py
zipper.egg-info/PKG-INFO
zipper.egg-info/SOURCES.txt
zipper.egg-info/dependency_links.txt
zipper.egg-info/top_level.txt