Metadata-Version: 1.1
Name: zipper
Version: 0.0.2
Summary: Functional hierarchical zipper, with navigation, editing, and enumeration.  See Huet
Home-page: http://github.com/trivio/zipper
Author: Scott Robertson
Author-email: scott@triv.io
License: UNKNOWN
Platform: UNKNOWN
Classifier: Programming Language :: Python
Classifier: License :: OSI Approved :: MIT License
Classifier: Operating System :: OS Independent
Classifier: Development Status :: 3 - Alpha
Classifier: Intended Audience :: Developers
Classifier: Topic :: Software Development
